pytrim2/__init__.py
pytrim2/_modidx.py
pytrim2/demultiplex.py
pytrim2-0.0.5.dist-info/LICENSE
pytrim2-0.0.5.dist-info/METADATA
pytrim2-0.0.5.dist-info/WHEEL
pytrim2-0.0.5.dist-info/entry_points.txt
pytrim2-0.0.5.dist-info/top_level.txt
pytrim2-0.0.5.dist-info/RECORD
