Metadata-Version: 2.1
Name: pytrim2
Version: 0.0.5
Summary: A python program to trim and demultiplex nanopore reads
Home-page: https://github.com/hcstubbe/pytrim2
Author: hcstubbe
Author-email: hstubbe@med.lmu.de
License: Apache Software License 2.0
Keywords: nbdev jupyter notebook python
Classifier: Development Status :: 4 - Beta
Classifier: Intended Audience :: Developers
Classifier: Natural Language :: English
Classifier: Programming Language :: Python :: 3.7
Classifier: Programming Language :: Python :: 3.8
Classifier: Programming Language :: Python :: 3.9
Classifier: Programming Language :: Python :: 3.10
Classifier: License :: OSI Approved :: Apache Software License
Requires-Python: >=3.7
License-File: LICENSE
Requires-Dist: numpy
Requires-Dist: biopython
Provides-Extra: dev
